MANIFEST.in
README.rst
setup.cfg
setup.py
versioneer.py
okera_fs_aws/__init__.py
okera_fs_aws/_version.py
okera_fs_aws.egg-info/PKG-INFO
okera_fs_aws.egg-info/SOURCES.txt
okera_fs_aws.egg-info/dependency_links.txt
okera_fs_aws.egg-info/not-zip-safe
okera_fs_aws.egg-info/requires.txt
okera_fs_aws.egg-info/top_level.txt
okera_fs_aws/plugin/__init__.py
okera_fs_aws/plugin/aws.py
okera_fs_aws/plugin/boto.py