Metadata-Version: 1.2
Name: okera-fs-aws
Version: 2.7.0b5
Summary: Python plugin supporting AWS CLI v1 for the Okera Data Access Service
Home-page: UNKNOWN
Maintainer: Okera Development Team
License: UNKNOWN
Platform: UNKNOWN
Classifier: Development Status :: 5 - Production/Stable
Classifier: Environment :: Console
Classifier: Operating System :: OS Independent
Classifier: Programming Language :: Python :: 2.7
Classifier: Programming Language :: Python :: 3.4
Classifier: Programming Language :: Python :: 3.5
Classifier: Programming Language :: Python :: 3.6
Classifier: Programming Language :: Python :: 3.7
Classifier: Programming Language :: Python :: 3.8
Classifier: Programming Language :: Python :: 3.9
